skillprofil/__init__.py
skillprofil/apps.py
skillprofil/domain/__init__.py
skillprofil/domain/hr.py
skillprofil/domain/authorization/__init__.py
skillprofil/domain/authorization/skillprofil_permission.py
skillprofil/domain/authorization/skillprofil_user.py
skillprofil/interfaces/__init__.py
skillprofil/interfaces/urls.py
skillprofil/interfaces/person/__init__.py
skillprofil/interfaces/person/person_serializer.py
skillprofil/interfaces/person/person_view.py
skillprofil/migrations/0001_initial.py
skillprofil/migrations/__init__.py
skillprofil/models/__init__.py
skillprofil/models/person.py
skillprofil/models/skill.py
skillprofil/tests/__init__.py
django_skillprofil-0.3.dist-info/LICENSE
django_skillprofil-0.3.dist-info/METADATA
django_skillprofil-0.3.dist-info/WHEEL
django_skillprofil-0.3.dist-info/top_level.txt
django_skillprofil-0.3.dist-info/RECORD
