Metadata-Version: 2.2
Name: django-skillprofil
Version: 0.3
Summary: A Django app to organize skillprofiles.
Author-email: Philipp Kroll <yourname@example.com>
Project-URL: Homepage, https://www.example.com/
Classifier: Environment :: Web Environment
Classifier: Framework :: Django
Classifier: Framework :: Django :: 5.0
Classifier: Intended Audience :: Developers
Classifier: License :: OSI Approved :: BSD License
Classifier: Operating System :: OS Independent
Classifier: Programming Language :: Python
Classifier: Programming Language :: Python :: 3
Classifier: Programming Language :: Python :: 3 :: Only
Classifier: Programming Language :: Python :: 3.10
Classifier: Programming Language :: Python :: 3.11
Classifier: Programming Language :: Python :: 3.12
Classifier: Programming Language :: Python :: 3.13
Classifier: Topic :: Internet :: WWW/HTTP
Classifier: Topic :: Internet :: WWW/HTTP :: Dynamic Content
Requires-Python: >=3.10
License-File: LICENSE
Requires-Dist: django>=5.0
Requires-Dist: drf_spectacular>=0.28.0
Requires-Dist: djangorestframework>=3.15.2
Requires-Dist: djangorestframework_simplejwt>=5.4.0
